T_tools
