Metadata-Version: 1.1
Name: tj-tools
Version: 0.0.7
Summary: tools
Home-page: https://github.com/Thixiaoxiao/MyTools
Author: chenxiyuxiao
Author-email: 18883325829@163.com
License: BSD 2-Clause License
Platform: UNKNOWN
Classifier: Programming Language :: Python
Classifier: Operating System :: Microsoft :: Windows
Classifier: Operating System :: Unix
Classifier: Programming Language :: Python :: 3.5
Classifier: Programming Language :: Python :: 3.6
Classifier: Programming Language :: Python :: 3.7
